rsserpent_rev/__init__.py
rsserpent_rev/log/__init__.py
rsserpent_rev/main.py
rsserpent_rev/models/__init__.py
rsserpent_rev/models/plugin.py
rsserpent_rev/models/rss.py
rsserpent_rev/plugins/__init__.py
rsserpent_rev/plugins/builtin/__init__.py
rsserpent_rev/plugins/builtin/example.py
rsserpent_rev/plugins/builtin/example_cache.py
rsserpent_rev/plugins/builtin/example_feedgen.py
rsserpent_rev/plugins/builtin/example_httpx.py
rsserpent_rev/plugins/builtin/example_log.py
rsserpent_rev/plugins/builtin/example_playwright.py
rsserpent_rev/plugins/builtin/example_pyquery.py
rsserpent_rev/plugins/builtin/example_ratelimit.py
rsserpent_rev/plugins/builtin/example_with_args.py
rsserpent_rev/plugins/externals.py
rsserpent_rev/py.typed
rsserpent_rev/templates/all_routes.html.jinja
rsserpent_rev/templates/exception.html.jinja
rsserpent_rev/templates/index.html.jinja
rsserpent_rev/utils/__init__.py
rsserpent_rev/utils/cache.py
rsserpent_rev/utils/http.py
rsserpent_rev/utils/provider.py
rsserpent_rev/utils/ratelimit.py
rsserpent_rev-0.1.7.dist-info/LICENSE
rsserpent_rev-0.1.7.dist-info/METADATA
rsserpent_rev-0.1.7.dist-info/WHEEL
rsserpent_rev-0.1.7.dist-info/RECORD
