Metadata-Version: 2.1
Name: rsserpent-rev
Version: 0.1.7
Summary: 🐍 This snake helps you reconnect the Web, with RSS feeds!
Home-page: https://github.com/RSSerpent-Rev/RSSerpent
License: MIT
Keywords: rss
Author: Queensferry
Author-email: queensferry.me@gmail.com
Requires-Python: >=3.10.0,<4.0.0
Classifier: Development Status :: 4 - Beta
Classifier: Environment :: Web Environment
Classifier: Framework :: AsyncIO
Classifier: Intended Audience :: Developers
Classifier: Intended Audience :: End Users/Desktop
Classifier: License :: OSI Approved :: MIT License
Classifier: Natural Language :: English
Classifier: Operating System :: OS Independent
Classifier: Programming Language :: Python
Classifier: Programming Language :: Python :: 3
Classifier: Programming Language :: Python :: 3.10
Classifier: Programming Language :: Python :: 3.11
Classifier: Programming Language :: Python :: 3.12
Classifier: Topic :: Internet :: WWW/HTTP :: Dynamic Content :: News/Diary
Classifier: Topic :: Software Development :: Libraries :: Python Modules
Classifier: Topic :: Utilities
Classifier: Typing :: Typed
Requires-Dist: Jinja2 (>=3.0.1,<4.0.0)
Requires-Dist: arrow (>=1.1.1,<2.0.0)
Requires-Dist: fake-useragent (>=0.1.11,<0.2.0)
Requires-Dist: feedgen (>=1.0.0,<2.0.0)
Requires-Dist: httpx (>=0.27.0,<0.28.0)
Requires-Dist: importlib-metadata (>=4.5.0,<5.0.0)
Requires-Dist: playwright (>=1.44.0,<2.0.0)
Requires-Dist: pydantic[email] (>=1.8.2,<2.0.0)
Requires-Dist: pyquery (>=1.4.3,<2.0.0)
Requires-Dist: starlette (==0.37.2)
Requires-Dist: types-lxml (>=2024.4.14,<2025.0.0)
Project-URL: Repository, https://github.com/RSSerpent-Rev/RSSerpent
